<xml><Event version="17.2.4.10" runNumber="191933" eventNumber="59487014" dataTime="2011-10-30 15:06:27 UTC">
<LAr3DEt>
1.5 0.9 25.4 0.7 1.7 0.8 0.6 0.8 0.6 1.2 1.2 0.8 0.8 1.1 </LAr3DEt>
<LAr3Dphi>
2 4 4 5 6 10 20 23 26 26 27 27 29 30 </LAr3Dphi>
<LAr3Dpsi>
28 0 12 15 30 2 22 6 20 21 1 20 3 21 </LAr3Dpsi>
<TILE3DEt>
0.9 1.2 0.8 1.3 </TILE3DEt>
<TILE3Dphi>
10 14 19 28 </TILE3Dphi>
<TILE3Dpsi>
6 22 6 5 </TILE3Dpsi>
<ETMis count="1" storeGateKey="MET_RefFinal">

<et>
242.237 
</et>
<etx>
-35.5956 
</etx>
<ety>
-19.4836 
</ety>
</ETMis>
<Track count="129" storeGateKey="Tracks">



<cotTheta>
-4.60478 5.26777 -4.53778 2.40701 3.19699 -2.43319 -3.58807 -4.04614 0.380421 4.00882
3.91642 3.29608 6.16715 -1.98407 -5.51088 -5.33727 -3.22796 -1.59707 -2.30426 -1.0101
0.0501826 -1.45203 -1.25376 0.130924 5.92013 0.602628 4.79671 -0.370612 -3.57428 2.43069
2.67002 -1.99222 1.32422 1.83534 3.50676 -2.35447 -0.651069 3.27643 0.0869788 3.62337
2.60435 -0.517048 2.82507 0.182739 3.11977 -2.21921 0.230374 -0.120663 -3.2484 -0.718752
0.216754 1.86453 -3.23153 1.95895 2.19178 2.7015 -4.46932 -1.02638 -0.480064 0.890322
2.95623 -0.0222568 -3.11347 4.64145 -1.21304 -3.99787 2.73238 1.58235 4.08586 2.4245
-0.777654 -0.568948 3.97578 -4.04863 1.87124 4.29656 1.02684 -1.38211 5.5866 1.38447
-0.392765 -1.48418 -0.0593822 1.99104 1.51812 1.17585 -0.751094 0.901318 3.60732 -6.49634
0.535695 -6.32814 6.3116 0.592211 -3.02152 3.81232 0.332195 -0.511308 1.07406 1.29878
0.239031 5.62788 -3.00332 3.0801 0.209668 1.36584 -4.0253 -3.64113 -1.09114 0.892957
0.0479386 0.242927 2.9006 1.03599 -3.12793 0.625763 0.987996 -1.70414 1.12547 -1.17285
-3.25394 1.08757 0.999503 0.34851 -0.347262 1.0974 0.931547 1.08058 -1.42479 
</cotTheta>

<d0>
0.104791 -0.0643779 -0.108723 -0.0179921 0.0584523 0.0201459 -0.101805 -0.131516 0.0748901 -0.0640396
-0.0347818 -0.089521 -0.117589 0.0138368 -0.0732562 0.0117189 0.0782368 -0.0766119 -0.0992601 0.0773363
0.0725501 -0.120191 0.017299 0.0597184 0.0279626 0.0734283 -0.0876705 -0.0968457 -0.0591777 -0.129587
0.0813269 -0.112345 0.0883823 0.0562381 -0.0084676 0.0114232 -0.216002 -0.0827312 0.0453398 -0.0017356
-0.039516 0.0296778 0.119277 0.036374 0.104577 -0.0204362 -0.071196 0.0435209 0.0488862 0.0477354
0.0803519 -0.0473981 0.139675 -0.0649359 0.0619814 0.0632723 0.0527987 0.0204912 -0.0280613 -0.0476243
-0.0486092 -0.0154611 0.0998103 0.11712 0.117781 0.169231 0.130543 0.0336159 -0.122221 0.0440955
-0.0161501 0.0819427 1.02554 0.0196822 0.0802976 -0.426632 0.0432634 -0.0654036 0.0225022 -0.117667
-0.00627021 0.000670598 -0.674352 0.390193 -0.131099 -0.307725 0.111391 -0.100829 -0.00702546 0.168426
0.000819108 0.00452105 -0.0399382 0.103686 -0.0250528 -0.159815 0.0148444 0.521522 0.328286 -0.0620062
-0.0208214 0.0953279 0.156229 0.011291 0.136264 0.270323 0.469694 -0.0346107 0.00300786 -0.8574
-0.151089 -0.737913 -0.399367 -0.232973 -0.0716618 -0.851187 -1.00461 -4.27258 2.31268 -0.474616
0.218054 -1.9425 2.80504 0.152197 0.422358 0.166317 9.215 6.00634 1.26137 
</d0>




<nPixHits>
6 6 5 4 3 4 4 4 3 5
3 3 5 3 5 5 3 3 3 4
3 3 4 3 5 3 3 4 4 3
4 4 3 3 3 3 3 3 3 5
3 3 3 3 3 3 3 3 3 3
3 3 3 3 3 3 3 3 3 3
3 3 3 5 3 3 3 4 4 2
3 3 3 4 4 3 4 3 7 3
2 3 2 3 3 2 2 3 2 3
2 3 5 3 2 2 2 2 2 2
2 5 2 2 2 2 2 2 3 1
1 1 1 1 1 0 0 0 0 0
0 0 0 0 0 0 0 0 0 
</nPixHits>
<nSCTHits>
10 8 11 12 12 12 9 8 8 9
11 10 8 11 8 7 10 12 9 8
11 9 8 10 8 10 9 8 8 10
8 8 9 8 10 8 8 9 10 6
8 8 8 8 8 8 8 8 8 8
8 8 8 8 8 8 8 8 8 8
8 8 8 7 8 11 7 6 8 11
7 6 8 5 4 8 4 5 0 5
8 4 8 10 9 8 8 10 8 4
8 4 2 4 10 10 9 10 10 9
9 3 8 8 8 8 8 8 4 8
8 8 8 8 6 8 8 5 0 0
0 0 0 0 0 0 0 0 0 
</nSCTHits>
<nTRTHits>
0 0 0 33 27 34 15 0 28 0
0 18 0 37 0 0 22 33 35 21
37 29 0 34 0 30 0 39 14 36
32 37 29 35 18 32 31 24 31 0
35 35 32 37 26 39 30 38 21 35
29 43 21 24 37 35 0 17 29 20
27 41 27 0 20 0 32 50 0 36
25 33 0 0 0 0 0 0 0 36
0 0 35 36 34 0 17 26 15 0
33 0 0 31 28 10 28 36 33 26
19 0 31 29 0 34 0 13 16 29
36 41 32 0 0 0 26 30 14 18
28 12 10 21 26 15 14 13 23 
</nTRTHits>


<numPolyline>
2 2 2 2 2 2 2 2 2 2
2 2 2 2 2 2 2 2 2 2
2 2 2 2 2 2 2 2 2 2
2 2 2 2 2 2 2 2 2 2
2 2 2 2 2 2 2 2 2 2
2 2 2 2 2 2 2 2 2 2
2 2 2 2 2 2 2 2 2 2
2 2 2 2 2 2 2 2 2 2
2 2 2 2 2 2 2 2 2 2
2 2 2 2 2 2 2 2 2 2
2 2 2 2 2 2 2 2 2 2
2 2 2 2 2 2 2 2 2 2
2 2 2 2 2 2 2 2 2 
</numPolyline>
<phi0>
0.349864 -1.99149 3.13922 2.14494 -1.13086 -1.3897 -2.80998 -3.01038 0.872251 -1.35191
-2.27343 -3.07017 -2.7033 1.39944 -2.11018 2.21254 0.596346 -2.35719 2.71426 0.816859
1.17506 2.7815 -1.29668 -0.918391 -1.76585 -0.87342 2.0979 -3.00467 -2.33561 -2.84527
0.854909 2.83908 -0.73074 -0.965846 1.69851 -1.37113 -2.66433 2.87385 -1.01528 -1.88576
1.96789 1.41092 -0.0991097 1.386 -0.167033 -1.54421 2.89958 -1.20252 -0.881446 -0.477056
-0.975278 -1.72762 0.797702 -2.15154 0.732173 0.601464 -0.874024 1.38573 -1.96216 -1.96334
2.27333 -1.68664 0.739419 -0.389452 -0.84045 -0.0402443 0.121082 1.40946 2.5352 1.95497
2.0594 0.625755 -1.20898 0.635803 -0.182892 -0.852867 -1.00105 -1.76771 1.3808 -2.56692
1.65007 -1.56347 -3.12124 -0.848021 2.17595 -2.24462 -0.12165 -2.97273 -1.76941 2.3435
-1.80623 0.414963 -1.10954 -0.500971 -1.39513 1.79578 -1.69873 2.30423 1.52351 -2.2147
1.23413 -1.08406 -2.02523 -0.538253 -0.608854 2.29932 -1.25267 2.58122 -1.76605 2.69546
-0.478743 2.04351 -2.14686 -3.12211 -1.60731 -1.35847 -2.91065 -2.45736 -0.762042 2.40477
0.412253 -0.314799 1.90145 0.487129 -0.653154 -0.474172 -2.31291 1.59583 2.55751 
</phi0>
<polylineX multiple="2">
4.7607 52.7617 -2.03763 -10.9769 -5.02946 -54.5744 -2.68366 -79.5279 2.21388 28.8319
0.811876 -29.6271 -4.9148 -72.5434 -5.19129 -51.7839 3.13086 66.0584 1.26002 23.9507
-3.33393 -28.0124 -5.20184 -80.1877 -4.95136 -42.0947 0.735919 -18.1794 -2.50474 -17.908
-2.9952 -32.2747 4.12534 60.2436 -3.55953 -38.5805 -4.75812 -83.1231 3.20791 23.7693
1.7607 -19.0781 -4.5941 -100.117 1.39408 5.46096 3.21203 95.3842 -1.10725 -19.5399
3.38067 98.6884 -2.39078 -18.0522 -4.8291 -79.1094 -3.43841 -24.1371 -4.85756 -85.655
3.13639 24.0481 -4.61978 -63.6128 3.75889 95.3529 2.90128 64.5462 -0.487951 19.7588
1.12188 42.2835 -4.38874 -80.2456 -4.76442 -65.0202 2.72115 104.487 -1.83659 -26.8495
-1.89142 -54.849 0.835084 57.9704 4.83078 86.0086 0.735066 -44.1876 4.77911 86.3017
0.207542 37.5704 -4.94001 -104.204 1.74231 -15.8219 3.3536 67.6707 4.63436 50.925
2.64622 -11.9218 -0.709219 38.8402 3.42352 74.5426 -3.12084 -93.5971 3.49152 26.2493
4.12691 43.2327 3.45444 40.7036 0.764472 -29.2501 -2.07593 -84.777 -1.94153 -2.16679
-3.04371 -17.7747 -0.432393 75.1485 3.40248 32.7565 4.53573 41.6136 3.67685 81.3746
5.05173 51.598 4.74233 74.9819 0.899168 77.6329 -3.96024 -37.722 -1.78162 -0.663815
-2.23725 5.21773 4.07105 69.4386 4.05365 16.8195 4.10365 38.0355 4.70797 36.9302
3.01808 38.508 2.73931 24.4375 -1.19211 -25.4213 0.774717 1.48818 -4.30539 -95.4351
-0.413303 -8.30064 0.0819316 2.80276 -4.84983 -100.73 3.95889 97.9533 -5.22453 -85.1495
-3.45916 -38.8773 4.90102 79.4114 -8.84617 -51.9498 -1.11402 -36.5616 -3.65721 -20.0541
-1.30701 -86.1023 4.34946 34.3419 2.42591 20.1579 4.63332 67.214 0.765831 -10.2916
-1.27995 14.1846 -0.803568 31.9481 -6.50736 -101.183 -0.426076 -65.0109 -5.11676 -32.4403
2.42448 -42.9422 2.39831 14.5744 -3.40621 -2.85925 7.90826 86.1996 7.23127 34.0306
-5.77986 -33.3448 3.48134 25.4373 -7.60698 -69.2843 -1.06198 -31.8243 -3.87136 -26.3955
10.6578 77.6795 -2.91726 1.93448 -3.30382 -80.2857 -12.2309 -42.9091 -0.150381 6.05845
0.0711646 -1.98256 -4.80921 -95.6171 -33.7843 -89.8244 58.3146 74.0961 -42.9398 -75.7021
57.7057 74.1179 76.2563 91.609 -26.1316 -40.4224 69.1191 87.9735 43.9815 61.0787
76.283 93.3368 -68.682 -79.69 -20.6524 -27.8762 -51.6331 -68.8902 
</polylineX>
<polylineY multiple="2">
1.75293 9.88217 -4.68055 -49.7142 0.200165 8.96737 4.02118 59.8437 -4.64048 -78.6322
-5.06195 -95.6793 -1.50299 -10.4429 -0.50224 -1.94691 3.8493 80.8764 -5.15247 -43.2122
-4.02123 -47.0004 -0.322498 -14.185 -2.09058 -13.7889 4.85901 96.6849 -4.22359 -46.6724
3.88945 34.2873 2.96301 56.5727 -3.5829 -90.2077 2.3297 55.5241 3.69859 96.2175
4.7454 102.189 1.76022 -1.99047 -5.25544 -51.7169 -3.92418 -44.6368 -4.84719 -39.7331
-3.75453 -41.0362 4.47088 48.8898 -0.690513 -66.95 -3.74493 -67.8452 -1.42012 -52.3335
3.93343 93.0711 1.69915 74.5856 -3.11989 -30.6413 -4.03829 -71.8506 4.87698 74.4648
-5.12817 -90.265 -2.07319 -61.5954 1.52583 47.8164 -4.00735 -22.6246 -4.98061 -36.5421
4.48883 83.7819 4.81364 89.7946 -0.451324 -38.0479 4.8172 96.2932 -0.625794 5.62219
-4.96842 -91.359 1.18745 -20.721 -4.7156 -103.979 -3.80761 -41.8266 -2.50986 -79.2934
-4.03825 -97.0747 -5.14932 -90.7142 3.4811 24.4571 -4.29639 -28.5592 3.40655 96.4736
3.08986 83.3199 -3.78555 -26.6036 4.84098 91.96 -4.65142 -64.4378 -4.81703 -97.9925
3.91122 82.5393 -5.29822 -75.3624 3.41571 79.4176 -1.76055 -19.1923 -3.73999 -34.457
0.0812548 10.2982 0.847608 56.264 4.7299 62.4551 2.82475 20.5879 4.54231 100.314
4.56084 87.5105 3.11206 79.8979 -8.05322 -49.0075 2.95368 21.1614 -0.717081 -2.37048
-3.9173 -28.0087 -4.01744 -27.7905 -4.86089 -44.2886 4.79842 11.6027 -2.44609 13.9025
4.80499 50.427 -4.9575 -36.9751 0.649718 34.5986 -3.60076 -14.4538 7.21011 52.2491
-3.69375 -33.3624 -0.320947 56.3887 -2.02473 -84.3186 -4.88668 -64.0182 3.68809 27.3156
-4.81156 -62.7651 2.097 27.9715 -4.58546 -25.9899 -2.51762 -71.7947 -5.04016 -84.8099
8.83766 67.5275 -8.78743 -99.5023 5.71665 9.42669 8.70621 76.3233 -7.10943 -94.0638
8.35378 95.4173 -4.58017 -42.1791 -8.30036 -88.0442 -4.15712 -6.07588 -5.32053 -38.1062
6.50947 92.4635 -8.13331 -45.1408 4.40523 19.7673 -4.94113 -67.1601 2.99226 96.2234
-6.12859 -73.2381 8.0275 105.311 -4.03579 -39.7127 -0.702219 -9.79066 -5.41958 -43.84
-4.86038 -50.8812 0.00653044 25.9649 -17.6847 -39.7759 -52.1971 -67.0967 38.4493 65.8873
28.5365 37.3882 -31.7653 -38.9547 59.8763 91.4162 41.1243 53.9194 -47.9762 -84.165
-28.8867 -32.9298 -57.1439 -60.9355 78.1452 96.2174 46.5543 72.5277 
</polylineY>
<polylineZ multiple="2">
-21.3737 -249.661 27.3042 273.742 -22.6318 -249.655 11.621 245.954 18.5783 270.122
-12.5905 -252.153 -22.901 -270.206 -21.0632 -210.216 1.97365 39.8141 32.5731 210.76
15.9846 210.775 17.3652 268.645 35.0163 274.297 -7.67435 -197.455 -25.7192 -273.622
-25.095 -249.714 -18.9641 -270.202 -9.95565 -164.611 -16.9554 -235.609 -3.07144 -102.266
2.16172 8.05285 -11.9781 -154.529 3.36107 -55.4027 10.9684 25.4463 32.4505 273.735
-1.80765 62.8795 25.5947 249.201 -6.69714 -46.0359 -23.2464 -268.666 7.45805 242.931
13.3118 262.759 -12.7412 -211.323 6.74419 136.863 11.1654 179.568 11.9157 270.126
-12.4408 -236.994 -8.07441 -71.151 18.1361 270.151 -2.80296 6.15137 29.8475 175.887
14.3275 264.257 -7.35861 -60.8733 13.8185 270.107 0.98792 21.7582 13.312 268.613
-11.1224 -221.599 -2.09773 22.4184 -3.84172 -16.6041 -19.4711 -268.655 -3.68004 -70.5084
2.91194 24.6923 10.0274 195.921 -18.1335 -270.169 12.4068 217.163 10.5829 233.786
10.9826 270.127 -12.7318 -210.649 -7.80591 -104.834 7.79653 -43.0095 6.58936 90.6558
16.243 268.646 -3.40632 -6.34546 -14.59 -270.213 20.9885 210.759 -4.597 -114.204
-18.71 -210.69 13.2168 270.106 2.4934 163.76 21.4278 178.849 12.0462 249.198
-3.81987 -70.9474 -7.7362 -65.7178 39.823 210.225 -20.0901 -178.592 9.08991 69.4655
21.4223 210.764 15.3183 48.4583 -4.92757 -70.4253 26.9006 65.1725 8.79067 143.445
0.0326663 -18.1085 -10.3958 -58.0882 -5.20928 -10.9888 12.9745 214.252 15.3463 159.435
5.95804 60.3883 6.55953 -70.6701 6.51081 100.493 18.5288 268.639 -28.6629 -213.691
4.64423 63.9729 -30.3362 -273.549 33.0506 213.235 3.30286 60.2473 -19.1634 -268.637
33.3915 270.141 -1.98862 30.6777 -18.5998 -69.4553 3.82691 112.547 6.66458 126.002
3.84188 28.95 27.3497 249.185 -25.2995 -270.127 22.66 270.116 23.5809 32.3914
8.55251 132.673 -38.1796 -210.682 -34.6211 -270.219 4.66405 -71.1326 4.70589 100.657
1.45451 6.08459 -1.90979 23.2257 10.639 270.144 11.81 45.0004 -16.3967 -138.557
3.2073 32.3056 5.18066 102.138 -87.0295 -189.98 88.0104 112.437 -67.5277 -117.668
-209.497 -270.189 89.7765 108.215 65.1862 99.7953 28.0376 35.9805 -22.7755 -36.7158
89.7949 109.041 85.6638 96.5541 86.4378 107.487 -99.8447 -144.397 
</polylineZ>
<pt>
0.858035 -0.671773 0.950695 -0.802184 2.49396 0.591401 1.02177 1.63162 -24.0359 -0.479309
-0.915792 -2.0347 0.951214 -0.806343 -0.773833 -1.20904 -1.36673 -0.77822 1.71091 -0.618847
-0.580069 -0.789976 0.904872 -0.697439 0.42236 -0.714908 0.810566 -0.585401 -0.451871 -1.10607
-0.566247 0.542472 -0.734683 -2.2066 0.559809 -1.16283 -1.69398 0.584254 -0.458161 0.417488
-1.48908 0.813678 0.77879 -0.563087 -0.951505 -0.773276 -0.756194 0.654219 -0.658419 0.557011
0.45095 -0.535083 0.44899 0.450651 -0.51765 -0.533073 -0.471432 -0.604351 0.665925 -0.837234
0.47285 -0.426661 -0.529649 2.98018 -0.651969 -0.662417 -0.501672 0.430654 -1.22252 0.75326
0.517553 -1.40285 2.82309 0.956379 -0.95685 -0.592257 -0.734101 0.491113 -0.576063 0.432492
-1.84277 -1.63807 0.947287 -0.429855 -0.729384 0.841278 -0.437506 -0.405243 0.620932 0.64678
0.498153 -0.433446 -0.467813 0.960668 0.765432 0.423106 -0.753798 -0.457298 -0.444986 -0.966629
-0.460919 0.676513 -0.564483 -0.504041 0.661607 0.780461 -0.795793 -0.666278 0.887829 0.400004
1.19477 0.674195 0.465733 -0.646863 -0.739463 0.657151 0.639905 1.23493 -97.2621 -11.6499
-4.12736 4.34559 -5.12768 -5.0545 1.07834 -2.20401 1.16353 -1.48904 1.23721 
</pt>

<z0>
1.99307 0.406973 0.195741 -0.0168687 2.14063 -0.114072 -4.46923 0.0275947 0.0862902 11.2991
-4.47491 0.186928 1.88668 2.07594 1.34973 1.10591 -2.57358 -1.88751 -4.75191 1.87186
1.90774 -4.83287 10.1787 10.3046 3.0008 -4.85129 1.2859 -4.88841 -5.06394 -4.84379
-0.115162 -2.94259 0.278384 2.04058 -5.27268 -0.0810265 -4.91611 1.75172 -3.2242 10.6072
1.6407 -4.83213 0.109173 0.0974771 -1.71742 -0.0851483 -3.26845 -3.235 -2.992 0.109423
1.86484 0.332504 -2.34353 2.00688 -0.105932 -2.94156 10.1676 -2.77578 10.2416 1.96463
1.5948 -3.28788 0.409947 -1.59018 1.76059 1.46278 0.0662876 -5.12774 1.55248 0.214317
0.130836 -4.82166 4.17097 0.383081 0.18169 0.206649 10.3261 1.98732 -0.254714 1.94098
1.92691 -3.03677 -4.92213 2.37416 1.82003 0.0246109 10.2454 -1.67974 0.446733 5.09014
1.97279 0.220338 0.295921 0.17952 -3.76066 -0.627946 -4.92021 -14.1917 -5.51377 -4.71474
1.76101 -1.7572 1.63269 -4.87081 21.6971 -3.34622 -2.6732 -2.59961 10.1789 0.430655
0.865398 -3.97059 -4.41027 -0.899481 0.567255 0.22379 0.555206 -23.0381 -0.0276522 0.105304
-0.0083263 0.0337621 0.0115559 -0.00291908 -0.0198679 0.112869 -0.0114479 -0.00621734 -0.0356469 
</z0>
</Track>
<Electron count="1" storeGateKey="ElectronCollection">

<author>
egamma 
</author>


<dataType>
1 
</dataType>
<eOverp>
1.16309 
</eOverp>
<energy>
29.9104 
</energy>
<eta>
0.371796 
</eta>
<hasTrack>
1 
</hasTrack>

<hitsPixel>
3 
</hitsPixel>
<hitsSCT>
8 
</hitsSCT>
<hitsTRT>
28 
</hitsTRT>

<isEMString>
TightPP 
</isEMString>

<mass>
0 
</mass>

<phi>
0.872251 
</phi>
<pt>
27.9558 
</pt>
<px>
17.9785 
</px>
<py>
21.408 
</py>
<pz>
10.635 
</pz>
<trackIndex>
5 
</trackIndex>

</Electron>
</Event></xml>